{
  "processing": {
    "model_gpu": "sam_b.pt",
    "model_cpu": "sam_b.pt",
    "max_side_cpu": 1536,
    "min_area_px": 50,
    "apply_feret_cap": true,
    "feret_cap_um": 5.0,
    "apply_ridge_filtering": false,
    "ridge_threshold": 0.15,
    "ridge_tv_weight": 0.01,
    "ridge_percentile": 70,
    "ridge_min_size": 50,
    "enable_tiling": true,
    "tile_size": 1024,
    "tile_overlap": 128,
    "min_image_size_for_tiling": 2048,
    "save_overlays": true,
    "save_contact_sheet": false,
    "annotate_measurements": true,
    "default_frame_width_um": 21.8
  },
  "variants": [
    {
      "name": "Balanced_Default_clahe_strong_8x8",
      "clip": 4.0,
      "tile": 8,
      "gamma": 1.0,
      "unsharp_amount": 0.7,
      "unsharp_sigma": 1.0
    },
    {
      "name": "Low_Contrast_clahe_strong_4x4",
      "clip": 8.0,
      "tile": 4,
      "gamma": 1.0,
      "unsharp_amount": 0.7,
      "unsharp_sigma": 1.0
    },
    {
      "name": "Low_Contrast_clahe_vstrong_4x4",
      "clip": 14.0,
      "tile": 4,
      "gamma": 1.0,
      "unsharp_amount": 0.7,
      "unsharp_sigma": 1.0
    },
    {
      "name": "Aggressive_clahe_vstrong_8x8",
      "clip": 15.0,
      "tile": 8,
      "gamma": 1.0,
      "unsharp_amount": 0.7,
      "unsharp_sigma": 1.0
    },
    {
      "name": "Aggressive_clahe_ultra_8x8",
      "clip": 20.0,
      "tile": 8,
      "gamma": 1.0,
      "unsharp_amount": 0.7,
      "unsharp_sigma": 1.0
    },
    {
      "name": "Ultra_Aggressive_clahe_ultra_4x4",
      "clip": 30.0,
      "tile": 4,
      "gamma": 1.0,
      "unsharp_amount": 0.7,
      "unsharp_sigma": 1.0
    }
  ]
}